CHANGES.md
bovine_herd/__init__.py
bovine_herd/add_to_queue.py
bovine_herd/server/__init__.py
bovine_herd/server/activitypub.py
bovine_herd/server/authorize.py
bovine_herd/server/endpoints.py
bovine_herd/server/objects/__init__.py
bovine_herd/server/objects/collection.py
bovine_herd/server/objects/ordered_collection.py
bovine_herd/server/objects/templates/fallback.html
bovine_herd/server/objects/test_object.py
bovine_herd/server/retrieve_public_key.py
bovine_herd/server/test_authorize.py
bovine_herd/server/test_path.py
bovine_herd/server/test_retrieve_public_key.py
bovine_herd/server/utils.py
bovine_herd/server/wellknown.py
bovine_herd/test.py
bovine_herd-0.5.19.dist-info/METADATA
bovine_herd-0.5.19.dist-info/WHEEL
bovine_herd-0.5.19.dist-info/RECORD
