Metadata-Version: 2.1
Name: bovine-herd
Version: 0.5.19
Summary: Implementation of a Fediverse server based on bovine
Home-page: https://codeberg.org/bovine/bovine
Author: Helge
Author-email: helge.krueger@gmail.com
Requires-Python: >=3.11,<4.0
Classifier: Intended Audience :: Developers
Classifier: License :: OSI Approved :: MIT License
Classifier: Programming Language :: Python :: 3
Classifier: Programming Language :: Python :: 3.11
Classifier: Programming Language :: Python :: 3.11
Classifier: Programming Language :: Python :: 3.12
Classifier: Topic :: Communications
Classifier: Topic :: Software Development :: Libraries :: Python Modules
Requires-Dist: bovine-process (>=0.5.19,<0.6.0)
Requires-Dist: bovine-store (>=0.5.19,<0.6.0)
Requires-Dist: quart (>=0.19.2,<0.20.0)
Project-URL: Documentation, https://bovine-herd.readthedocs.io/en/latest/
Project-URL: Repository, https://codeberg.org/bovine/bovine
